{".class":"MypyFile","_fullname":"music21.tree.analysis","future_import_flags":["annotations"],"is_partial_stub_package":false,"is_stub":false,"names":{".class":"SymbolTable","Horizontality":{".class":"SymbolTableNode","kind":"Gdef","node":{".class":"TypeInfo","_promote":[],"abstract_attributes":[],"alt_promote":null,"bases":[{".class":"Instance","args":[{".class":"AnyType","missing_import_name":null,"source_any":null,"type_of_any":4}],"extra_attrs":null,"type_ref":"typing.Sequence"}],"dataclass_transform_spec":null,"declared_metaclass":null,"defn":{".class":"ClassDef","fullname":"music21.tree.analysis.Horizontality","name":"Horizontality","type_vars":[]},"deletable_attributes":[],"deprecated":null,"flags":[],"fullname":"music21.tree.analysis.Horizontality","has_param_spec_type":false,"metaclass_type":"abc.ABCMeta","metadata":{},"module_name":"music21.tree.analysis","mro":["music21.tree.analysis.Horizontality","typing.Sequence","typing.Reversible","typing.Collection","typing.Iterable","typing.Container","builtins.object"],"names":{".class":"SymbolTable","__getitem__":{".class":"SymbolTableNode","kind":"Mdef","node":{".class":"FuncDef","abstract_status":0,"arg_kinds":[0,0],"arg_names":[null,null],"dataclass_transform_spec":null,"deprecated":null,"flags":[],"fullname":"music21.tree.analysis.Horizontality.__getitem__","name":"__getitem__","type":null}},"__init__":{".class":"SymbolTableNode","kind":"Mdef","node":{".class":"FuncDef","abstract_status":0,"arg_kinds":[0,1],"arg_names":["self","timespans"],"dataclass_transform_spec":null,"deprecated":null,"flags":[],"fullname":"music21.tree.analysis.Horizontality.__init__","name":"__init__","type":null}},"__len__":{".class":"SymbolTableNode","kind":"Mdef","node":{".class":"FuncDef","abstract_status":0,"arg_kinds":[0],"arg_names":[null],"dataclass_transform_spec":null,"deprecated":null,"flags":[],"fullname":"music21.tree.analysis.Horizontality.__len__","name":"__len__","type":null}},"__repr__":{".class":"SymbolTableNode","kind":"Mdef","node":{".class":"FuncDef","abstract_status":0,"arg_kinds":[0],"arg_names":[null],"dataclass_transform_spec":null,"deprecated":null,"flags":[],"fullname":"music21.tree.analysis.Horizontality.__repr__","name":"__repr__","type":null}},"__slots__":{".class":"SymbolTableNode","kind":"Mdef","node":{".class":"Var","flags":["is_initialized_in_class","is_inferred","has_explicit_value","allow_incompatible_override"],"fullname":"music21.tree.analysis.Horizontality.__slots__","name":"__slots__","type":{".class":"TupleType","implicit":false,"items":["builtins.str"],"partial_fallback":{".class":"Instance","args":[{".class":"AnyType","missing_import_name":null,"source_any":null,"type_of_any":6}],"extra_attrs":null,"type_ref":"builtins.tuple"}}}},"hasNeighborTone":{".class":"SymbolTableNode","kind":"Mdef","node":{".class":"Decorator","func":{".class":"FuncDef","abstract_status":0,"arg_kinds":[0],"arg_names":["self"],"dataclass_transform_spec":null,"deprecated":null,"flags":["is_property","is_decorated"],"fullname":"music21.tree.analysis.Horizontality.hasNeighborTone","name":"hasNeighborTone","type":null},"is_overload":false,"var":{".class":"Var","flags":["is_initialized_in_class","is_property","is_ready","is_inferred"],"fullname":"music21.tree.analysis.Horizontality.hasNeighborTone","name":"hasNeighborTone","type":{".class":"CallableType","arg_kinds":[0],"arg_names":["self"],"arg_types":["music21.tree.analysis.Horizontality"],"bound_args":[],"def_extras":{"first_arg":"self"},"fallback":"builtins.function","from_concatenate":false,"implicit":true,"imprecise_arg_kinds":false,"is_ellipsis_args":false,"name":"hasNeighborTone of Horizontality","ret_type":{".class":"AnyType","missing_import_name":null,"source_any":null,"type_of_any":1},"type_guard":null,"type_is":null,"unpack_kwargs":false,"variables":[]}}}},"hasNoMotion":{".class":"SymbolTableNode","kind":"Mdef","node":{".class":"Decorator","func":{".class":"FuncDef","abstract_status":0,"arg_kinds":[0],"arg_names":["self"],"dataclass_transform_spec":null,"deprecated":null,"flags":["is_property","is_decorated"],"fullname":"music21.tree.analysis.Horizontality.hasNoMotion","name":"hasNoMotion","type":null},"is_overload":false,"var":{".class":"Var","flags":["is_initialized_in_class","is_property","is_ready","is_inferred"],"fullname":"music21.tree.analysis.Horizontality.hasNoMotion","name":"hasNoMotion","type":{".class":"CallableType","arg_kinds":[0],"arg_names":["self"],"arg_types":["music21.tree.analysis.Horizontality"],"bound_args":[],"def_extras":{"first_arg":"self"},"fallback":"builtins.function","from_concatenate":false,"implicit":true,"imprecise_arg_kinds":false,"is_ellipsis_args":false,"name":"hasNoMotion of Horizontality","ret_type":{".class":"AnyType","missing_import_name":null,"source_any":null,"type_of_any":1},"type_guard":null,"type_is":null,"unpack_kwargs":false,"variables":[]}}}},"hasPassingTone":{".class":"SymbolTableNode","kind":"Mdef","node":{".class":"Decorator","func":{".class":"FuncDef","abstract_status":0,"arg_kinds":[0],"arg_names":["self"],"dataclass_transform_spec":null,"deprecated":null,"flags":["is_property","is_decorated"],"fullname":"music21.tree.analysis.Horizontality.hasPassingTone","name":"hasPassingTone","type":null},"is_overload":false,"var":{".class":"Var","flags":["is_initialized_in_class","is_property","is_ready","is_inferred"],"fullname":"music21.tree.analysis.Horizontality.hasPassingTone","name":"hasPassingTone","type":{".class":"CallableType","arg_kinds":[0],"arg_names":["self"],"arg_types":["music21.tree.analysis.Horizontality"],"bound_args":[],"def_extras":{"first_arg":"self"},"fallback":"builtins.function","from_concatenate":false,"implicit":true,"imprecise_arg_kinds":false,"is_ellipsis_args":false,"name":"hasPassingTone of Horizontality","ret_type":{".class":"AnyType","missing_import_name":null,"source_any":null,"type_of_any":1},"type_guard":null,"type_is":null,"unpack_kwargs":false,"variables":[]}}}},"timespans":{".class":"SymbolTableNode","implicit":true,"kind":"Mdef","node":{".class":"Var","flags":["is_inferred"],"fullname":"music21.tree.analysis.Horizontality.timespans","name":"timespans","type":{".class":"AnyType","missing_import_name":null,"source_any":null,"type_of_any":1}}}},"self_type":{".class":"TypeVarType","default":{".class":"AnyType","missing_import_name":null,"source_any":null,"type_of_any":4},"fullname":"music21.tree.analysis.Horizontality.Self","id":0,"name":"Self","namespace":"","upper_bound":"music21.tree.analysis.Horizontality","values":[],"variance":0},"slots":null,"tuple_type":null,"type_vars":[],"typeddict_type":null}},"HorizontalityException":{".class":"SymbolTableNode","kind":"Gdef","node":{".class":"TypeInfo","_promote":[],"abstract_attributes":[],"alt_promote":null,"bases":["music21.exceptions21.TreeException"],"dataclass_transform_spec":null,"declared_metaclass":null,"defn":{".class":"ClassDef","fullname":"music21.tree.analysis.HorizontalityException","name":"HorizontalityException","type_vars":[]},"deletable_attributes":[],"deprecated":null,"flags":[],"fullname":"music21.tree.analysis.HorizontalityException","has_param_spec_type":false,"metaclass_type":null,"metadata":{},"module_name":"music21.tree.analysis","mro":["music21.tree.analysis.HorizontalityException","music21.exceptions21.TreeException","music21.exceptions21.Music21Exception","builtins.Exception","builtins.BaseException","builtins.object"],"names":{".class":"SymbolTable"},"self_type":{".class":"TypeVarType","default":{".class":"AnyType","missing_import_name":null,"source_any":null,"type_of_any":4},"fullname":"music21.tree.analysis.HorizontalityException.Self","id":0,"name":"Self","namespace":"","upper_bound":"music21.tree.analysis.HorizontalityException","values":[],"variance":0},"slots":null,"tuple_type":null,"type_vars":[],"typeddict_type":null}},"Test":{".class":"SymbolTableNode","kind":"Gdef","node":{".class":"TypeInfo","_promote":[],"abstract_attributes":[],"alt_promote":null,"bases":["unittest.case.TestCase"],"dataclass_transform_spec":null,"declared_metaclass":null,"defn":{".class":"ClassDef","fullname":"music21.tree.analysis.Test","name":"Test","type_vars":[]},"deletable_attributes":[],"deprecated":null,"flags":[],"fullname":"music21.tree.analysis.Test","has_param_spec_type":false,"metaclass_type":null,"metadata":{},"module_name":"music21.tree.analysis","mro":["music21.tree.analysis.Test","unittest.case.TestCase","builtins.object"],"names":{".class":"SymbolTable"},"self_type":{".class":"TypeVarType","default":{".class":"AnyType","missing_import_name":null,"source_any":null,"type_of_any":4},"fullname":"music21.tree.analysis.Test.Self","id":0,"name":"Self","namespace":"","upper_bound":"music21.tree.analysis.Test","values":[],"variance":0},"slots":null,"tuple_type":null,"type_vars":[],"typeddict_type":null}},"_DOC_ORDER":{".class":"SymbolTableNode","kind":"Gdef","node":{".class":"Var","flags":["is_inferred","has_explicit_value"],"fullname":"music21.tree.analysis._DOC_ORDER","name":"_DOC_ORDER","type":{".class":"TupleType","implicit":false,"items":[],"partial_fallback":{".class":"Instance","args":[{".class":"AnyType","missing_import_name":null,"source_any":null,"type_of_any":6}],"extra_attrs":null,"type_ref":"builtins.tuple"}}}},"__annotations__":{".class":"SymbolTableNode","kind":"Gdef","node":{".class":"Var","flags":["is_ready"],"fullname":"music21.tree.analysis.__annotations__","name":"__annotations__","type":{".class":"Instance","args":["builtins.str",{".class":"AnyType","missing_import_name":null,"source_any":null,"type_of_any":6}],"extra_attrs":null,"type_ref":"builtins.dict"}}},"__doc__":{".class":"SymbolTableNode","kind":"Gdef","node":{".class":"Var","flags":["is_ready"],"fullname":"music21.tree.analysis.__doc__","name":"__doc__","type":"builtins.str"}},"__file__":{".class":"SymbolTableNode","kind":"Gdef","node":{".class":"Var","flags":["is_ready"],"fullname":"music21.tree.analysis.__file__","name":"__file__","type":"builtins.str"}},"__name__":{".class":"SymbolTableNode","kind":"Gdef","node":{".class":"Var","flags":["is_ready"],"fullname":"music21.tree.analysis.__name__","name":"__name__","type":"builtins.str"}},"__package__":{".class":"SymbolTableNode","kind":"Gdef","node":{".class":"Var","flags":["is_ready"],"fullname":"music21.tree.analysis.__package__","name":"__package__","type":"builtins.str"}},"__spec__":{".class":"SymbolTableNode","kind":"Gdef","node":{".class":"Var","flags":["is_ready"],"fullname":"music21.tree.analysis.__spec__","name":"__spec__","type":"_frozen_importlib.ModuleSpec"}},"annotations":{".class":"SymbolTableNode","cross_ref":"__future__.annotations","kind":"Gdef"},"collections":{".class":"SymbolTableNode","cross_ref":"collections","kind":"Gdef"},"environLocal":{".class":"SymbolTableNode","kind":"Gdef","node":{".class":"Var","flags":["is_inferred","has_explicit_value"],"fullname":"music21.tree.analysis.environLocal","name":"environLocal","type":"music21.environment.Environment"}},"environment":{".class":"SymbolTableNode","cross_ref":"music21.environment","kind":"Gdef"},"exceptions21":{".class":"SymbolTableNode","cross_ref":"music21.exceptions21","kind":"Gdef"},"music21":{".class":"SymbolTableNode","cross_ref":"music21","kind":"Gdef"},"unittest":{".class":"SymbolTableNode","cross_ref":"unittest","kind":"Gdef"}},"path":"C:\\Users\\12502\\AppData\\Roaming\\Python\\Python313\\site-packages\\music21\\tree\\analysis.py"}