{"data_mtime":1751371743,"dep_lines":[54,55,64,1596,1608,1659,2034,2152,2245,40,57,58,59,60,61,62,63,68,618,1596,1623,1664,1665,1739,1782,1794,1837,1860,1870,1907,2034,2168,2213,36,38,39,41,42,43,44,45,46,47,48,49,50,57,1976,1,1,1,1,1,1,1,1,1,1,1,1,1,1,1,1,1,1,52],"dep_prios":[10,10,10,20,20,20,20,20,20,5,10,10,10,10,10,10,10,25,20,20,20,20,20,20,20,20,20,20,20,20,20,20,20,5,5,10,10,5,10,10,10,10,10,10,10,10,10,20,5,20,20,20,30,30,30,30,30,30,30,30,30,30,30,30,30,30,10],"dependencies":["music21.converter.subConverters","music21.converter.museScore","music21.metadata.bundles","music21.musicxml.testFiles","music21.musicxml.testPrimitive","music21.test.commonTest","music21.abcFormat.testFiles","music21.mei.base","music21.humdrum.spineParser","http.client","music21._version","music21.common","music21.environment","music21.exceptions21","music21.metadata","music21.musedata","music21.stream","music21.base","music21.freezeThaw","music21.musicxml","music21.corpus","music21.dynamics","music21.note","music21.chord","music21.clef","music21.meter","music21.key","music21.bar","music21.layout","music21.instrument","music21.abcFormat","music21.omr","music21.harmony","__future__","collections","copy","io","math","os","re","pathlib","sys","types","typing","unittest","zipfile","music21","fractions","builtins","music21.text","music21.converter","pickle","_collections_abc","_frozen_importlib","abc","enum","music21.common.enums","music21.common.formats","music21.common.pathTools","music21.prebase","music21.stream.base","music21.stream.core","music21.stream.enums","music21.test","music21.test.testRunner","unittest.case"],"hash":"111ae8533d6297ef2a3b41fcf81bdd5f1a05feeb","id":"music21.converter","ignore_all":true,"interface_hash":"fd0c4e040ef36ade11ebd694f75ab3bb39934d77","mtime":1746077546,"options":{"allow_redefinition":false,"allow_untyped_globals":false,"always_false":[],"always_true":[],"bazel":false,"check_untyped_defs":false,"disable_bytearray_promotion":false,"disable_error_code":[],"disable_memoryview_promotion":false,"disabled_error_codes":[],"disallow_any_decorated":false,"disallow_any_explicit":false,"disallow_any_expr":false,"disallow_any_generics":false,"disallow_any_unimported":false,"disallow_incomplete_defs":false,"disallow_subclassing_any":false,"disallow_untyped_calls":false,"disallow_untyped_decorators":false,"disallow_untyped_defs":false,"enable_error_code":[],"enabled_error_codes":[],"extra_checks":false,"follow_imports":"normal","follow_imports_for_stubs":false,"follow_untyped_imports":false,"ignore_errors":false,"ignore_missing_imports":false,"implicit_optional":false,"implicit_reexport":true,"local_partial_types":false,"mypyc":false,"old_type_inference":false,"platform":"win32","plugins":[],"strict_concatenate":false,"strict_equality":false,"strict_optional":true,"warn_no_return":true,"warn_return_any":false,"warn_unreachable":false,"warn_unused_ignores":false},"path":"C:\\Users\\12502\\AppData\\Roaming\\Python\\Python313\\site-packages\\music21\\converter\\__init__.py","plugin_data":null,"size":88203,"suppressed":["requests"],"version_id":"1.14.1"}