{".class":"MypyFile","_fullname":"music21.repeat","future_import_flags":["annotations"],"is_partial_stub_package":false,"is_stub":false,"names":{".class":"SymbolTable","AlSegno":{".class":"SymbolTableNode","kind":"Gdef","node":{".class":"TypeInfo","_promote":[],"abstract_attributes":[],"alt_promote":null,"bases":["music21.repeat.RepeatExpressionCommand"],"dataclass_transform_spec":null,"declared_metaclass":null,"defn":{".class":"ClassDef","fullname":"music21.repeat.AlSegno","name":"AlSegno","type_vars":[]},"deletable_attributes":[],"deprecated":null,"flags":[],"fullname":"music21.repeat.AlSegno","has_param_spec_type":false,"metaclass_type":null,"metadata":{},"module_name":"music21.repeat","mro":["music21.repeat.AlSegno","music21.repeat.RepeatExpressionCommand","music21.repeat.RepeatExpression","music21.repeat.RepeatMark","music21.expressions.Expression","music21.base.Music21Object","music21.prebase.ProtoM21Object","builtins.object"],"names":{".class":"SymbolTable","__init__":{".class":"SymbolTableNode","kind":"Mdef","node":{".class":"FuncDef","abstract_status":0,"arg_kinds":[0,1,4],"arg_names":["self","text","keywords"],"dataclass_transform_spec":null,"deprecated":null,"flags":[],"fullname":"music21.repeat.AlSegno.__init__","name":"__init__","type":null}}},"self_type":{".class":"TypeVarType","default":{".class":"AnyType","missing_import_name":null,"source_any":null,"type_of_any":4},"fullname":"music21.repeat.AlSegno.Self","id":0,"name":"Self","namespace":"","upper_bound":"music21.repeat.AlSegno","values":[],"variance":0},"slots":null,"tuple_type":null,"type_vars":[],"typeddict_type":null}},"Coda":{".class":"SymbolTableNode","kind":"Gdef","node":{".class":"TypeInfo","_promote":[],"abstract_attributes":[],"alt_promote":null,"bases":["music21.repeat.RepeatExpressionMarker"],"dataclass_transform_spec":null,"declared_metaclass":null,"defn":{".class":"ClassDef","fullname":"music21.repeat.Coda","name":"Coda","type_vars":[]},"deletable_attributes":[],"deprecated":null,"flags":[],"fullname":"music21.repeat.Coda","has_param_spec_type":false,"metaclass_type":null,"metadata":{},"module_name":"music21.repeat","mro":["music21.repeat.Coda","music21.repeat.RepeatExpressionMarker","music21.repeat.RepeatExpression","music21.repeat.RepeatMark","music21.expressions.Expression","music21.base.Music21Object","music21.prebase.ProtoM21Object","builtins.object"],"names":{".class":"SymbolTable","__init__":{".class":"SymbolTableNode","kind":"Mdef","node":{".class":"FuncDef","abstract_status":0,"arg_kinds":[0,1,4],"arg_names":["self","text","keywords"],"dataclass_transform_spec":null,"deprecated":null,"flags":[],"fullname":"music21.repeat.Coda.__init__","name":"__init__","type":null}}},"self_type":{".class":"TypeVarType","default":{".class":"AnyType","missing_import_name":null,"source_any":null,"type_of_any":4},"fullname":"music21.repeat.Coda.Self","id":0,"name":"Self","namespace":"","upper_bound":"music21.repeat.Coda","values":[],"variance":0},"slots":null,"tuple_type":null,"type_vars":[],"typeddict_type":null}},"DaCapo":{".class":"SymbolTableNode","kind":"Gdef","node":{".class":"TypeInfo","_promote":[],"abstract_attributes":[],"alt_promote":null,"bases":["music21.repeat.RepeatExpressionCommand"],"dataclass_transform_spec":null,"declared_metaclass":null,"defn":{".class":"ClassDef","fullname":"music21.repeat.DaCapo","name":"DaCapo","type_vars":[]},"deletable_attributes":[],"deprecated":null,"flags":[],"fullname":"music21.repeat.DaCapo","has_param_spec_type":false,"metaclass_type":null,"metadata":{},"module_name":"music21.repeat","mro":["music21.repeat.DaCapo","music21.repeat.RepeatExpressionCommand","music21.repeat.RepeatExpression","music21.repeat.RepeatMark","music21.expressions.Expression","music21.base.Music21Object","music21.prebase.ProtoM21Object","builtins.object"],"names":{".class":"SymbolTable","__init__":{".class":"SymbolTableNode","kind":"Mdef","node":{".class":"FuncDef","abstract_status":0,"arg_kinds":[0,1,4],"arg_names":["self","text","keywords"],"dataclass_transform_spec":null,"deprecated":null,"flags":[],"fullname":"music21.repeat.DaCapo.__init__","name":"__init__","type":null}}},"self_type":{".class":"TypeVarType","default":{".class":"AnyType","missing_import_name":null,"source_any":null,"type_of_any":4},"fullname":"music21.repeat.DaCapo.Self","id":0,"name":"Self","namespace":"","upper_bound":"music21.repeat.DaCapo","values":[],"variance":0},"slots":null,"tuple_type":null,"type_vars":[],"typeddict_type":null}},"DaCapoAlCoda":{".class":"SymbolTableNode","kind":"Gdef","node":{".class":"TypeInfo","_promote":[],"abstract_attributes":[],"alt_promote":null,"bases":["music21.repeat.RepeatExpressionCommand"],"dataclass_transform_spec":null,"declared_metaclass":null,"defn":{".class":"ClassDef","fullname":"music21.repeat.DaCapoAlCoda","name":"DaCapoAlCoda","type_vars":[]},"deletable_attributes":[],"deprecated":null,"flags":[],"fullname":"music21.repeat.DaCapoAlCoda","has_param_spec_type":false,"metaclass_type":null,"metadata":{},"module_name":"music21.repeat","mro":["music21.repeat.DaCapoAlCoda","music21.repeat.RepeatExpressionCommand","music21.repeat.RepeatExpression","music21.repeat.RepeatMark","music21.expressions.Expression","music21.base.Music21Object","music21.prebase.ProtoM21Object","builtins.object"],"names":{".class":"SymbolTable","__init__":{".class":"SymbolTableNode","kind":"Mdef","node":{".class":"FuncDef","abstract_status":0,"arg_kinds":[0,1,4],"arg_names":["self","text","keywords"],"dataclass_transform_spec":null,"deprecated":null,"flags":[],"fullname":"music21.repeat.DaCapoAlCoda.__init__","name":"__init__","type":null}}},"self_type":{".class":"TypeVarType","default":{".class":"AnyType","missing_import_name":null,"source_any":null,"type_of_any":4},"fullname":"music21.repeat.DaCapoAlCoda.Self","id":0,"name":"Self","namespace":"","upper_bound":"music21.repeat.DaCapoAlCoda","values":[],"variance":0},"slots":null,"tuple_type":null,"type_vars":[],"typeddict_type":null}},"DaCapoAlFine":{".class":"SymbolTableNode","kind":"Gdef","node":{".class":"TypeInfo","_promote":[],"abstract_attributes":[],"alt_promote":null,"bases":["music21.repeat.RepeatExpressionCommand"],"dataclass_transform_spec":null,"declared_metaclass":null,"defn":{".class":"ClassDef","fullname":"music21.repeat.DaCapoAlFine","name":"DaCapoAlFine","type_vars":[]},"deletable_attributes":[],"deprecated":null,"flags":[],"fullname":"music21.repeat.DaCapoAlFine","has_param_spec_type":false,"metaclass_type":null,"metadata":{},"module_name":"music21.repeat","mro":["music21.repeat.DaCapoAlFine","music21.repeat.RepeatExpressionCommand","music21.repeat.RepeatExpression","music21.repeat.RepeatMark","music21.expressions.Expression","music21.base.Music21Object","music21.prebase.ProtoM21Object","builtins.object"],"names":{".class":"SymbolTable","__init__":{".class":"SymbolTableNode","kind":"Mdef","node":{".class":"FuncDef","abstract_status":0,"arg_kinds":[0,1,4],"arg_names":["self","text","keywords"],"dataclass_transform_spec":null,"deprecated":null,"flags":[],"fullname":"music21.repeat.DaCapoAlFine.__init__","name":"__init__","type":null}}},"self_type":{".class":"TypeVarType","default":{".class":"AnyType","missing_import_name":null,"source_any":null,"type_of_any":4},"fullname":"music21.repeat.DaCapoAlFine.Self","id":0,"name":"Self","namespace":"","upper_bound":"music21.repeat.DaCapoAlFine","values":[],"variance":0},"slots":null,"tuple_type":null,"type_vars":[],"typeddict_type":null}},"DalSegno":{".class":"SymbolTableNode","kind":"Gdef","node":{".class":"TypeInfo","_promote":[],"abstract_attributes":[],"alt_promote":null,"bases":["music21.repeat.RepeatExpressionCommand"],"dataclass_transform_spec":null,"declared_metaclass":null,"defn":{".class":"ClassDef","fullname":"music21.repeat.DalSegno","name":"DalSegno","type_vars":[]},"deletable_attributes":[],"deprecated":null,"flags":[],"fullname":"music21.repeat.DalSegno","has_param_spec_type":false,"metaclass_type":null,"metadata":{},"module_name":"music21.repeat","mro":["music21.repeat.DalSegno","music21.repeat.RepeatExpressionCommand","music21.repeat.RepeatExpression","music21.repeat.RepeatMark","music21.expressions.Expression","music21.base.Music21Object","music21.prebase.ProtoM21Object","builtins.object"],"names":{".class":"SymbolTable","__init__":{".class":"SymbolTableNode","kind":"Mdef","node":{".class":"FuncDef","abstract_status":0,"arg_kinds":[0,1,4],"arg_names":["self","text","keywords"],"dataclass_transform_spec":null,"deprecated":null,"flags":[],"fullname":"music21.repeat.DalSegno.__init__","name":"__init__","type":null}}},"self_type":{".class":"TypeVarType","default":{".class":"AnyType","missing_import_name":null,"source_any":null,"type_of_any":4},"fullname":"music21.repeat.DalSegno.Self","id":0,"name":"Self","namespace":"","upper_bound":"music21.repeat.DalSegno","values":[],"variance":0},"slots":null,"tuple_type":null,"type_vars":[],"typeddict_type":null}},"DalSegnoAlCoda":{".class":"SymbolTableNode","kind":"Gdef","node":{".class":"TypeInfo","_promote":[],"abstract_attributes":[],"alt_promote":null,"bases":["music21.repeat.RepeatExpressionCommand"],"dataclass_transform_spec":null,"declared_metaclass":null,"defn":{".class":"ClassDef","fullname":"music21.repeat.DalSegnoAlCoda","name":"DalSegnoAlCoda","type_vars":[]},"deletable_attributes":[],"deprecated":null,"flags":[],"fullname":"music21.repeat.DalSegnoAlCoda","has_param_spec_type":false,"metaclass_type":null,"metadata":{},"module_name":"music21.repeat","mro":["music21.repeat.DalSegnoAlCoda","music21.repeat.RepeatExpressionCommand","music21.repeat.RepeatExpression","music21.repeat.RepeatMark","music21.expressions.Expression","music21.base.Music21Object","music21.prebase.ProtoM21Object","builtins.object"],"names":{".class":"SymbolTable","__init__":{".class":"SymbolTableNode","kind":"Mdef","node":{".class":"FuncDef","abstract_status":0,"arg_kinds":[0,1,4],"arg_names":["self","text","keywords"],"dataclass_transform_spec":null,"deprecated":null,"flags":[],"fullname":"music21.repeat.DalSegnoAlCoda.__init__","name":"__init__","type":null}}},"self_type":{".class":"TypeVarType","default":{".class":"AnyType","missing_import_name":null,"source_any":null,"type_of_any":4},"fullname":"music21.repeat.DalSegnoAlCoda.Self","id":0,"name":"Self","namespace":"","upper_bound":"music21.repeat.DalSegnoAlCoda","values":[],"variance":0},"slots":null,"tuple_type":null,"type_vars":[],"typeddict_type":null}},"DalSegnoAlFine":{".class":"SymbolTableNode","kind":"Gdef","node":{".class":"TypeInfo","_promote":[],"abstract_attributes":[],"alt_promote":null,"bases":["music21.repeat.RepeatExpressionCommand"],"dataclass_transform_spec":null,"declared_metaclass":null,"defn":{".class":"ClassDef","fullname":"music21.repeat.DalSegnoAlFine","name":"DalSegnoAlFine","type_vars":[]},"deletable_attributes":[],"deprecated":null,"flags":[],"fullname":"music21.repeat.DalSegnoAlFine","has_param_spec_type":false,"metaclass_type":null,"metadata":{},"module_name":"music21.repeat","mro":["music21.repeat.DalSegnoAlFine","music21.repeat.RepeatExpressionCommand","music21.repeat.RepeatExpression","music21.repeat.RepeatMark","music21.expressions.Expression","music21.base.Music21Object","music21.prebase.ProtoM21Object","builtins.object"],"names":{".class":"SymbolTable","__init__":{".class":"SymbolTableNode","kind":"Mdef","node":{".class":"FuncDef","abstract_status":0,"arg_kinds":[0,1,4],"arg_names":["self","text","keywords"],"dataclass_transform_spec":null,"deprecated":null,"flags":[],"fullname":"music21.repeat.DalSegnoAlFine.__init__","name":"__init__","type":null}}},"self_type":{".class":"TypeVarType","default":{".class":"AnyType","missing_import_name":null,"source_any":null,"type_of_any":4},"fullname":"music21.repeat.DalSegnoAlFine.Self","id":0,"name":"Self","namespace":"","upper_bound":"music21.repeat.DalSegnoAlFine","values":[],"variance":0},"slots":null,"tuple_type":null,"type_vars":[],"typeddict_type":null}},"Expander":{".class":"SymbolTableNode","kind":"Gdef","node":{".class":"TypeInfo","_promote":[],"abstract_attributes":[],"alt_promote":null,"bases":["builtins.object"],"dataclass_transform_spec":null,"declared_metaclass":null,"defn":{".class":"ClassDef","fullname":"music21.repeat.Expander","name":"Expander","type_vars":[{".class":"TypeVarType","default":{".class":"AnyType","missing_import_name":null,"source_any":null,"type_of_any":4},"fullname":"music21.common.types.StreamType","id":1,"name":"StreamType","namespace":"music21.repeat.Expander","upper_bound":{".class":"Instance","args":[{".class":"AnyType","missing_import_name":null,"source_any":null,"type_of_any":4}],"extra_attrs":null,"type_ref":"music21.stream.base.Stream"},"values":[],"variance":0}]},"deletable_attributes":[],"deprecated":null,"flags":[],"fullname":"music21.repeat.Expander","has_param_spec_type":false,"metaclass_type":null,"metadata":{},"module_name":"music21.repeat","mro":["music21.repeat.Expander","builtins.object"],"names":{".class":"SymbolTable","_DOC_ORDER":{".class":"SymbolTableNode","kind":"Mdef","node":{".class":"Var","flags":["is_initialized_in_class","is_inferred","has_explicit_value"],"fullname":"music21.repeat.Expander._DOC_ORDER","name":"_DOC_ORDER","type":{".class":"Instance","args":["builtins.str"],"extra_attrs":null,"type_ref":"builtins.list"}}},"__init__":{".class":"SymbolTableNode","kind":"Mdef","node":{".class":"FuncDef","abstract_status":0,"arg_kinds":[0,0],"arg_names":["self","streamObj"],"dataclass_transform_spec":null,"deprecated":null,"flags":[],"fullname":"music21.repeat.Expander.__init__","name":"__init__","type":{".class":"CallableType","arg_kinds":[0,0],"arg_names":["self","streamObj"],"arg_types":[{".class":"Instance","args":[{".class":"TypeVarType","default":{".class":"AnyType","missing_import_name":null,"source_any":null,"type_of_any":4},"fullname":"music21.common.types.StreamType","id":1,"name":"StreamType","namespace":"music21.repeat.Expander","upper_bound":{".class":"Instance","args":[{".class":"AnyType","missing_import_name":null,"source_any":null,"type_of_any":4}],"extra_attrs":null,"type_ref":"music21.stream.base.Stream"},"values":[],"variance":0}],"extra_attrs":null,"type_ref":"music21.repeat.Expander"},{".class":"TypeVarType","default":{".class":"AnyType","missing_import_name":null,"source_any":null,"type_of_any":4},"fullname":"music21.common.types.StreamType","id":1,"name":"StreamType","namespace":"music21.repeat.Expander","upper_bound":{".class":"Instance","args":[{".class":"AnyType","missing_import_name":null,"source_any":null,"type_of_any":4}],"extra_attrs":null,"type_ref":"music21.stream.base.Stream"},"values":[],"variance":0}],"bound_args":[],"def_extras":{"first_arg":"self"},"fallback":"builtins.function","from_concatenate":false,"implicit":false,"imprecise_arg_kinds":false,"is_ellipsis_args":false,"name":"__init__ of Expander","ret_type":{".class":"NoneType"},"type_guard":null,"type_is":null,"unpack_kwargs":false,"variables":[]}}},"_asCount":{".class":"SymbolTableNode","implicit":true,"kind":"Mdef","node":{".class":"Var","flags":["is_inferred"],"fullname":"music21.repeat.Expander._asCount","name":"_asCount","type":"builtins.int"}},"_codaCount":{".class":"SymbolTableNode","implicit":true,"kind":"Mdef","node":{".class":"Var","flags":["is_inferred"],"fullname":"music21.repeat.Expander._codaCount","name":"_codaCount","type":"builtins.int"}},"_daCapoIsCoherent":{".class":"SymbolTableNode","kind":"Mdef","node":{".class":"FuncDef","abstract_status":0,"arg_kinds":[0],"arg_names":["self"],"dataclass_transform_spec":null,"deprecated":null,"flags":[],"fullname":"music21.repeat.Expander._daCapoIsCoherent","name":"_daCapoIsCoherent","type":null}},"_daCapoOrSegno":{".class":"SymbolTableNode","kind":"Mdef","node":{".class":"FuncDef","abstract_status":0,"arg_kinds":[0],"arg_names":["self"],"dataclass_transform_spec":null,"deprecated":null,"flags":[],"fullname":"music21.repeat.Expander._daCapoOrSegno","name":"_daCapoOrSegno","type":null}},"_dalSegnoIsCoherent":{".class":"SymbolTableNode","kind":"Mdef","node":{".class":"FuncDef","abstract_status":0,"arg_kinds":[0],"arg_names":["self"],"dataclass_transform_spec":null,"deprecated":null,"flags":[],"fullname":"music21.repeat.Expander._dalSegnoIsCoherent","name":"_dalSegnoIsCoherent","type":null}},"_dcCount":{".class":"SymbolTableNode","implicit":true,"kind":"Mdef","node":{".class":"Var","flags":["is_inferred"],"fullname":"music21.repeat.Expander._dcCount","name":"_dcCount","type":"builtins.int"}},"_dcacCount":{".class":"SymbolTableNode","implicit":true,"kind":"Mdef","node":{".class":"Var","flags":["is_inferred"],"fullname":"music21.repeat.Expander._dcacCount","name":"_dcacCount","type":"builtins.int"}},"_dcafCount":{".class":"SymbolTableNode","implicit":true,"kind":"Mdef","node":{".class":"Var","flags":["is_inferred"],"fullname":"music21.repeat.Expander._dcafCount","name":"_dcafCount","type":"builtins.int"}},"_dsCount":{".class":"SymbolTableNode","implicit":true,"kind":"Mdef","node":{".class":"Var","flags":["is_inferred"],"fullname":"music21.repeat.Expander._dsCount","name":"_dsCount","type":"builtins.int"}},"_dsacCount":{".class":"SymbolTableNode","implicit":true,"kind":"Mdef","node":{".class":"Var","flags":["is_inferred"],"fullname":"music21.repeat.Expander._dsacCount","name":"_dsacCount","type":"builtins.int"}},"_dsafCount":{".class":"SymbolTableNode","implicit":true,"kind":"Mdef","node":{".class":"Var","flags":["is_inferred"],"fullname":"music21.repeat.Expander._dsafCount","name":"_dsafCount","type":"builtins.int"}},"_fineCount":{".class":"SymbolTableNode","implicit":true,"kind":"Mdef","node":{".class":"Var","flags":["is_inferred"],"fullname":"music21.repeat.Expander._fineCount","name":"_fineCount","type":"builtins.int"}},"_getEndRepeatBar":{".class":"SymbolTableNode","kind":"Mdef","node":{".class":"FuncDef","abstract_status":0,"arg_kinds":[0,0,0],"arg_names":["self","streamObj","index"],"dataclass_transform_spec":null,"deprecated":null,"flags":[],"fullname":"music21.repeat.Expander._getEndRepeatBar","name":"_getEndRepeatBar","type":null}},"_getRepeatExpressionCommand":{".class":"SymbolTableNode","kind":"Mdef","node":{".class":"FuncDef","abstract_status":0,"arg_kinds":[0,0],"arg_names":["self","streamObj"],"dataclass_transform_spec":null,"deprecated":null,"flags":[],"fullname":"music21.repeat.Expander._getRepeatExpressionCommand","name":"_getRepeatExpressionCommand","type":null}},"_getRepeatExpressionCommandType":{".class":"SymbolTableNode","kind":"Mdef","node":{".class":"FuncDef","abstract_status":0,"arg_kinds":[0],"arg_names":["self"],"dataclass_transform_spec":null,"deprecated":null,"flags":[],"fullname":"music21.repeat.Expander._getRepeatExpressionCommandType","name":"_getRepeatExpressionCommandType","type":null}},"_groupRepeatBracketIndices":{".class":"SymbolTableNode","kind":"Mdef","node":{".class":"FuncDef","abstract_status":0,"arg_kinds":[0,0],"arg_names":["self","streamObj"],"dataclass_transform_spec":null,"deprecated":null,"flags":[],"fullname":"music21.repeat.Expander._groupRepeatBracketIndices","name":"_groupRepeatBracketIndices","type":null}},"_hasRepeat":{".class":"SymbolTableNode","kind":"Mdef","node":{".class":"FuncDef","abstract_status":0,"arg_kinds":[0,0],"arg_names":["self","streamObj"],"dataclass_transform_spec":null,"deprecated":null,"flags":[],"fullname":"music21.repeat.Expander._hasRepeat","name":"_hasRepeat","type":{".class":"CallableType","arg_kinds":[0,0],"arg_names":["self","streamObj"],"arg_types":[{".class":"Instance","args":[{".class":"TypeVarType","default":{".class":"AnyType","missing_import_name":null,"source_any":null,"type_of_any":4},"fullname":"music21.common.types.StreamType","id":1,"name":"StreamType","namespace":"music21.repeat.Expander","upper_bound":{".class":"Instance","args":[{".class":"AnyType","missing_import_name":null,"source_any":null,"type_of_any":4}],"extra_attrs":null,"type_ref":"music21.stream.base.Stream"},"values":[],"variance":0}],"extra_attrs":null,"type_ref":"music21.repeat.Expander"},{".class":"Instance","args":[{".class":"AnyType","missing_import_name":null,"source_any":null,"type_of_any":4}],"extra_attrs":null,"type_ref":"music21.stream.base.Stream"}],"bound_args":[],"def_extras":{"first_arg":"self"},"fallback":"builtins.function","from_concatenate":false,"implicit":false,"imprecise_arg_kinds":false,"is_ellipsis_args":false,"name":"_hasRepeat of Expander","ret_type":"builtins.bool","type_guard":null,"type_is":null,"unpack_kwargs":false,"variables":[]}}},"_processInnermostRepeatsAndBrackets":{".class":"SymbolTableNode","kind":"Mdef","node":{".class":"FuncDef","abstract_status":0,"arg_kinds":[0,0,1],"arg_names":["self","streamObj","repeatBracketsMemo"],"dataclass_transform_spec":null,"deprecated":null,"flags":[],"fullname":"music21.repeat.Expander._processInnermostRepeatsAndBrackets","name":"_processInnermostRepeatsAndBrackets","type":null}},"_processRecursiveRepeatBars":{".class":"SymbolTableNode","kind":"Mdef","node":{".class":"FuncDef","abstract_status":0,"arg_kinds":[0,0,1],"arg_names":["self","streamObj","makeDeepCopy"],"dataclass_transform_spec":null,"deprecated":null,"flags":[],"fullname":"music21.repeat.Expander._processRecursiveRepeatBars","name":"_processRecursiveRepeatBars","type":null}},"_processRepeatExpressionAndRepeats":{".class":"SymbolTableNode","kind":"Mdef","node":{".class":"FuncDef","abstract_status":0,"arg_kinds":[0,0],"arg_names":["self","streamObj"],"dataclass_transform_spec":null,"deprecated":null,"flags":[],"fullname":"music21.repeat.Expander._processRepeatExpressionAndRepeats","name":"_processRepeatExpressionAndRepeats","type":null}},"_repeatBrackets":{".class":"SymbolTableNode","implicit":true,"kind":"Mdef","node":{".class":"Var","flags":["explicit_self_type","is_ready","is_inferred"],"fullname":"music21.repeat.Expander._repeatBrackets","name":"_repeatBrackets","type":{".class":"Instance","args":["music21.spanner.RepeatBracket"],"extra_attrs":null,"type_ref":"music21.stream.base.Stream"}}},"_repeatBracketsAreCoherent":{".class":"SymbolTableNode","kind":"Mdef","node":{".class":"FuncDef","abstract_status":0,"arg_kinds":[0],"arg_names":["self"],"dataclass_transform_spec":null,"deprecated":null,"flags":[],"fullname":"music21.repeat.Expander._repeatBracketsAreCoherent","name":"_repeatBracketsAreCoherent","type":null}},"_segnoCount":{".class":"SymbolTableNode","implicit":true,"kind":"Mdef","node":{".class":"Var","flags":["is_inferred"],"fullname":"music21.repeat.Expander._segnoCount","name":"_segnoCount","type":"builtins.int"}},"_src":{".class":"SymbolTableNode","implicit":true,"kind":"Mdef","node":{".class":"Var","flags":["explicit_self_type","is_ready","is_inferred"],"fullname":"music21.repeat.Expander._src","name":"_src","type":{".class":"TypeVarType","default":{".class":"AnyType","missing_import_name":null,"source_any":null,"type_of_any":4},"fullname":"music21.common.types.StreamType","id":1,"name":"StreamType","namespace":"music21.repeat.Expander","upper_bound":{".class":"Instance","args":[{".class":"AnyType","missing_import_name":null,"source_any":null,"type_of_any":4}],"extra_attrs":null,"type_ref":"music21.stream.base.Stream"},"values":[],"variance":0}}},"_srcMeasureCount":{".class":"SymbolTableNode","implicit":true,"kind":"Mdef","node":{".class":"Var","flags":["explicit_self_type","is_ready","is_inferred"],"fullname":"music21.repeat.Expander._srcMeasureCount","name":"_srcMeasureCount","type":"builtins.int"}},"_srcMeasureStream":{".class":"SymbolTableNode","implicit":true,"kind":"Mdef","node":{".class":"Var","flags":["explicit_self_type","is_ready","is_inferred"],"fullname":"music21.repeat.Expander._srcMeasureStream","name":"_srcMeasureStream","type":{".class":"Instance","args":["music21.stream.base.Measure"],"extra_attrs":null,"type_ref":"music21.stream.base.Stream"}}},"_stripRepeatBarlines":{".class":"SymbolTableNode","kind":"Mdef","node":{".class":"FuncDef","abstract_status":0,"arg_kinds":[0,0,1],"arg_names":["self","m","newType"],"dataclass_transform_spec":null,"deprecated":null,"flags":[],"fullname":"music21.repeat.Expander._stripRepeatBarlines","name":"_stripRepeatBarlines","type":null}},"_stripRepeatExpressions":{".class":"SymbolTableNode","kind":"Mdef","node":{".class":"FuncDef","abstract_status":0,"arg_kinds":[0,0],"arg_names":["self","streamObj"],"dataclass_transform_spec":null,"deprecated":null,"flags":[],"fullname":"music21.repeat.Expander._stripRepeatExpressions","name":"_stripRepeatExpressions","type":{".class":"CallableType","arg_kinds":[0,0],"arg_names":["self","streamObj"],"arg_types":[{".class":"Instance","args":[{".class":"TypeVarType","default":{".class":"AnyType","missing_import_name":null,"source_any":null,"type_of_any":4},"fullname":"music21.common.types.StreamType","id":1,"name":"StreamType","namespace":"music21.repeat.Expander","upper_bound":{".class":"Instance","args":[{".class":"AnyType","missing_import_name":null,"source_any":null,"type_of_any":4}],"extra_attrs":null,"type_ref":"music21.stream.base.Stream"},"values":[],"variance":0}],"extra_attrs":null,"type_ref":"music21.repeat.Expander"},{".class":"Instance","args":[{".class":"AnyType","missing_import_name":null,"source_any":null,"type_of_any":4}],"extra_attrs":null,"type_ref":"music21.stream.base.Stream"}],"bound_args":[],"def_extras":{"first_arg":"self"},"fallback":"builtins.function","from_concatenate":false,"implicit":false,"imprecise_arg_kinds":false,"is_ellipsis_args":false,"name":"_stripRepeatExpressions of Expander","ret_type":{".class":"AnyType","missing_import_name":null,"source_any":null,"type_of_any":1},"type_guard":null,"type_is":null,"unpack_kwargs":false,"variables":[]}}},"findInnermostRepeatIndices":{".class":"SymbolTableNode","kind":"Mdef","node":{".class":"FuncDef","abstract_status":0,"arg_kinds":[0,0],"arg_names":["self","streamObj"],"dataclass_transform_spec":null,"deprecated":null,"flags":[],"fullname":"music21.repeat.Expander.findInnermostRepeatIndices","name":"findInnermostRepeatIndices","type":null}},"getRepeatExpressionIndex":{".class":"SymbolTableNode","kind":"Mdef","node":{".class":"FuncDef","abstract_status":0,"arg_kinds":[0,0,0],"arg_names":["self","streamObj","target"],"dataclass_transform_spec":null,"deprecated":null,"flags":[],"fullname":"music21.repeat.Expander.getRepeatExpressionIndex","name":"getRepeatExpressionIndex","type":null}},"isExpandable":{".class":"SymbolTableNode","kind":"Mdef","node":{".class":"FuncDef","abstract_status":0,"arg_kinds":[0],"arg_names":["self"],"dataclass_transform_spec":null,"deprecated":null,"flags":[],"fullname":"music21.repeat.Expander.isExpandable","name":"isExpandable","type":{".class":"CallableType","arg_kinds":[0],"arg_names":["self"],"arg_types":[{".class":"Instance","args":[{".class":"TypeVarType","default":{".class":"AnyType","missing_import_name":null,"source_any":null,"type_of_any":4},"fullname":"music21.common.types.StreamType","id":1,"name":"StreamType","namespace":"music21.repeat.Expander","upper_bound":{".class":"Instance","args":[{".class":"AnyType","missing_import_name":null,"source_any":null,"type_of_any":4}],"extra_attrs":null,"type_ref":"music21.stream.base.Stream"},"values":[],"variance":0}],"extra_attrs":null,"type_ref":"music21.repeat.Expander"}],"bound_args":[],"def_extras":{"first_arg":"self"},"fallback":"builtins.function","from_concatenate":false,"implicit":false,"imprecise_arg_kinds":false,"is_ellipsis_args":false,"name":"isExpandable of Expander","ret_type":{".class":"UnionType","items":["builtins.bool",{".class":"NoneType"}],"uses_pep604_syntax":true},"type_guard":null,"type_is":null,"unpack_kwargs":false,"variables":[]}}},"measureMap":{".class":"SymbolTableNode","kind":"Mdef","node":{".class":"FuncDef","abstract_status":0,"arg_kinds":[0,1],"arg_names":["self","returnType"],"dataclass_transform_spec":null,"deprecated":null,"flags":[],"fullname":"music21.repeat.Expander.measureMap","name":"measureMap","type":null}},"process":{".class":"SymbolTableNode","kind":"Mdef","node":{".class":"FuncDef","abstract_status":0,"arg_kinds":[0,1],"arg_names":["self","deepcopy"],"dataclass_transform_spec":null,"deprecated":null,"flags":[],"fullname":"music21.repeat.Expander.process","name":"process","type":{".class":"CallableType","arg_kinds":[0,1],"arg_names":["self","deepcopy"],"arg_types":[{".class":"Instance","args":[{".class":"TypeVarType","default":{".class":"AnyType","missing_import_name":null,"source_any":null,"type_of_any":4},"fullname":"music21.common.types.StreamType","id":1,"name":"StreamType","namespace":"music21.repeat.Expander","upper_bound":{".class":"Instance","args":[{".class":"AnyType","missing_import_name":null,"source_any":null,"type_of_any":4}],"extra_attrs":null,"type_ref":"music21.stream.base.Stream"},"values":[],"variance":0}],"extra_attrs":null,"type_ref":"music21.repeat.Expander"},"builtins.bool"],"bound_args":[],"def_extras":{"first_arg":"self"},"fallback":"builtins.function","from_concatenate":false,"implicit":false,"imprecise_arg_kinds":false,"is_ellipsis_args":false,"name":"process of Expander","ret_type":{".class":"TypeVarType","default":{".class":"AnyType","missing_import_name":null,"source_any":null,"type_of_any":4},"fullname":"music21.common.types.StreamType","id":1,"name":"StreamType","namespace":"music21.repeat.Expander","upper_bound":{".class":"Instance","args":[{".class":"AnyType","missing_import_name":null,"source_any":null,"type_of_any":4}],"extra_attrs":null,"type_ref":"music21.stream.base.Stream"},"values":[],"variance":0},"type_guard":null,"type_is":null,"unpack_kwargs":false,"variables":[]}}},"processInnermostRepeatBars":{".class":"SymbolTableNode","kind":"Mdef","node":{".class":"FuncDef","abstract_status":0,"arg_kinds":[0,0,1,1,1],"arg_names":["self","streamObj","repeatIndices","repeatTimes","returnExpansionOnly"],"dataclass_transform_spec":null,"deprecated":null,"flags":[],"fullname":"music21.repeat.Expander.processInnermostRepeatBars","name":"processInnermostRepeatBars","type":null}},"repeatBarsAreCoherent":{".class":"SymbolTableNode","kind":"Mdef","node":{".class":"FuncDef","abstract_status":0,"arg_kinds":[0],"arg_names":["self"],"dataclass_transform_spec":null,"deprecated":null,"flags":[],"fullname":"music21.repeat.Expander.repeatBarsAreCoherent","name":"repeatBarsAreCoherent","type":null}}},"self_type":{".class":"TypeVarType","default":{".class":"AnyType","missing_import_name":null,"source_any":null,"type_of_any":4},"fullname":"music21.repeat.Expander.Self","id":0,"name":"Self","namespace":"","upper_bound":{".class":"Instance","args":[{".class":"TypeVarType","default":{".class":"AnyType","missing_import_name":null,"source_any":null,"type_of_any":4},"fullname":"music21.common.types.StreamType","id":1,"name":"StreamType","namespace":"music21.repeat.Expander","upper_bound":{".class":"Instance","args":[{".class":"AnyType","missing_import_name":null,"source_any":null,"type_of_any":4}],"extra_attrs":null,"type_ref":"music21.stream.base.Stream"},"values":[],"variance":0}],"extra_attrs":null,"type_ref":"music21.repeat.Expander"},"values":[],"variance":0},"slots":null,"tuple_type":null,"type_vars":["StreamType"],"typeddict_type":null}},"ExpanderException":{".class":"SymbolTableNode","kind":"Gdef","node":{".class":"TypeInfo","_promote":[],"abstract_attributes":[],"alt_promote":null,"bases":["music21.exceptions21.Music21Exception"],"dataclass_transform_spec":null,"declared_metaclass":null,"defn":{".class":"ClassDef","fullname":"music21.repeat.ExpanderException","name":"ExpanderException","type_vars":[]},"deletable_attributes":[],"deprecated":null,"flags":[],"fullname":"music21.repeat.ExpanderException","has_param_spec_type":false,"metaclass_type":null,"metadata":{},"module_name":"music21.repeat","mro":["music21.repeat.ExpanderException","music21.exceptions21.Music21Exception","builtins.Exception","builtins.BaseException","builtins.object"],"names":{".class":"SymbolTable"},"self_type":{".class":"TypeVarType","default":{".class":"AnyType","missing_import_name":null,"source_any":null,"type_of_any":4},"fullname":"music21.repeat.ExpanderException.Self","id":0,"name":"Self","namespace":"","upper_bound":"music21.repeat.ExpanderException","values":[],"variance":0},"slots":null,"tuple_type":null,"type_vars":[],"typeddict_type":null}},"Fine":{".class":"SymbolTableNode","kind":"Gdef","node":{".class":"TypeInfo","_promote":[],"abstract_attributes":[],"alt_promote":null,"bases":["music21.repeat.RepeatExpressionMarker"],"dataclass_transform_spec":null,"declared_metaclass":null,"defn":{".class":"ClassDef","fullname":"music21.repeat.Fine","name":"Fine","type_vars":[]},"deletable_attributes":[],"deprecated":null,"flags":[],"fullname":"music21.repeat.Fine","has_param_spec_type":false,"metaclass_type":null,"metadata":{},"module_name":"music21.repeat","mro":["music21.repeat.Fine","music21.repeat.RepeatExpressionMarker","music21.repeat.RepeatExpression","music21.repeat.RepeatMark","music21.expressions.Expression","music21.base.Music21Object","music21.prebase.ProtoM21Object","builtins.object"],"names":{".class":"SymbolTable","__init__":{".class":"SymbolTableNode","kind":"Mdef","node":{".class":"FuncDef","abstract_status":0,"arg_kinds":[0,4],"arg_names":["self","keywords"],"dataclass_transform_spec":null,"deprecated":null,"flags":[],"fullname":"music21.repeat.Fine.__init__","name":"__init__","type":null}}},"self_type":{".class":"TypeVarType","default":{".class":"AnyType","missing_import_name":null,"source_any":null,"type_of_any":4},"fullname":"music21.repeat.Fine.Self","id":0,"name":"Self","namespace":"","upper_bound":"music21.repeat.Fine","values":[],"variance":0},"slots":null,"tuple_type":null,"type_vars":[],"typeddict_type":null}},"InsufficientLengthException":{".class":"SymbolTableNode","kind":"Gdef","node":{".class":"TypeInfo","_promote":[],"abstract_attributes":[],"alt_promote":null,"bases":["music21.exceptions21.Music21Exception"],"dataclass_transform_spec":null,"declared_metaclass":null,"defn":{".class":"ClassDef","fullname":"music21.repeat.InsufficientLengthException","name":"InsufficientLengthException","type_vars":[]},"deletable_attributes":[],"deprecated":null,"flags":[],"fullname":"music21.repeat.InsufficientLengthException","has_param_spec_type":false,"metaclass_type":null,"metadata":{},"module_name":"music21.repeat","mro":["music21.repeat.InsufficientLengthException","music21.exceptions21.Music21Exception","builtins.Exception","builtins.BaseException","builtins.object"],"names":{".class":"SymbolTable"},"self_type":{".class":"TypeVarType","default":{".class":"AnyType","missing_import_name":null,"source_any":null,"type_of_any":4},"fullname":"music21.repeat.InsufficientLengthException.Self","id":0,"name":"Self","namespace":"","upper_bound":"music21.repeat.InsufficientLengthException","values":[],"variance":0},"slots":null,"tuple_type":null,"type_vars":[],"typeddict_type":null}},"NoInternalStreamException":{".class":"SymbolTableNode","kind":"Gdef","node":{".class":"TypeInfo","_promote":[],"abstract_attributes":[],"alt_promote":null,"bases":["music21.exceptions21.Music21Exception"],"dataclass_transform_spec":null,"declared_metaclass":null,"defn":{".class":"ClassDef","fullname":"music21.repeat.NoInternalStreamException","name":"NoInternalStreamException","type_vars":[]},"deletable_attributes":[],"deprecated":null,"flags":[],"fullname":"music21.repeat.NoInternalStreamException","has_param_spec_type":false,"metaclass_type":null,"metadata":{},"module_name":"music21.repeat","mro":["music21.repeat.NoInternalStreamException","music21.exceptions21.Music21Exception","builtins.Exception","builtins.BaseException","builtins.object"],"names":{".class":"SymbolTable"},"self_type":{".class":"TypeVarType","default":{".class":"AnyType","missing_import_name":null,"source_any":null,"type_of_any":4},"fullname":"music21.repeat.NoInternalStreamException.Self","id":0,"name":"Self","namespace":"","upper_bound":"music21.repeat.NoInternalStreamException","values":[],"variance":0},"slots":null,"tuple_type":null,"type_vars":[],"typeddict_type":null}},"RepeatExpression":{".class":"SymbolTableNode","kind":"Gdef","node":{".class":"TypeInfo","_promote":[],"abstract_attributes":[],"alt_promote":null,"bases":["music21.repeat.RepeatMark","music21.expressions.Expression"],"dataclass_transform_spec":null,"declared_metaclass":null,"defn":{".class":"ClassDef","fullname":"music21.repeat.RepeatExpression","name":"RepeatExpression","type_vars":[]},"deletable_attributes":[],"deprecated":null,"flags":[],"fullname":"music21.repeat.RepeatExpression","has_param_spec_type":false,"metaclass_type":null,"metadata":{},"module_name":"music21.repeat","mro":["music21.repeat.RepeatExpression","music21.repeat.RepeatMark","music21.expressions.Expression","music21.base.Music21Object","music21.prebase.ProtoM21Object","builtins.object"],"names":{".class":"SymbolTable","__init__":{".class":"SymbolTableNode","kind":"Mdef","node":{".class":"FuncDef","abstract_status":0,"arg_kinds":[0,4],"arg_names":["self","keywords"],"dataclass_transform_spec":null,"deprecated":null,"flags":[],"fullname":"music21.repeat.RepeatExpression.__init__","name":"__init__","type":null}},"_reprInternal":{".class":"SymbolTableNode","kind":"Mdef","node":{".class":"FuncDef","abstract_status":0,"arg_kinds":[0],"arg_names":["self"],"dataclass_transform_spec":null,"deprecated":null,"flags":[],"fullname":"music21.repeat.RepeatExpression._reprInternal","name":"_reprInternal","type":null}},"_styleClass":{".class":"SymbolTableNode","kind":"Mdef","node":{".class":"Var","flags":["is_initialized_in_class","is_inferred","has_explicit_value"],"fullname":"music21.repeat.RepeatExpression._styleClass","name":"_styleClass","type":{".class":"CallableType","arg_kinds":[],"arg_names":[],"arg_types":[],"bound_args":["music21.style.TextStyle"],"def_extras":{"first_arg":"self"},"fallback":"builtins.type","from_concatenate":false,"implicit":true,"imprecise_arg_kinds":false,"is_ellipsis_args":false,"name":null,"ret_type":"music21.style.TextStyle","type_guard":null,"type_is":null,"unpack_kwargs":false,"variables":[]}}},"_textAlternatives":{".class":"SymbolTableNode","implicit":true,"kind":"Mdef","node":{".class":"Var","flags":["is_inferred"],"fullname":"music21.repeat.RepeatExpression._textAlternatives","name":"_textAlternatives","type":{".class":"AnyType","missing_import_name":null,"source_any":null,"type_of_any":1}}},"_textExpression":{".class":"SymbolTableNode","implicit":true,"kind":"Mdef","node":{".class":"Var","flags":["is_inferred"],"fullname":"music21.repeat.RepeatExpression._textExpression","name":"_textExpression","type":{".class":"AnyType","missing_import_name":null,"source_any":null,"type_of_any":1}}},"applyTextFormatting":{".class":"SymbolTableNode","kind":"Mdef","node":{".class":"FuncDef","abstract_status":0,"arg_kinds":[0,1],"arg_names":["self","te"],"dataclass_transform_spec":null,"deprecated":null,"flags":[],"fullname":"music21.repeat.RepeatExpression.applyTextFormatting","name":"applyTextFormatting","type":null}},"getText":{".class":"SymbolTableNode","kind":"Mdef","node":{".class":"FuncDef","abstract_status":0,"arg_kinds":[0],"arg_names":["self"],"dataclass_transform_spec":null,"deprecated":null,"flags":[],"fullname":"music21.repeat.RepeatExpression.getText","name":"getText","type":null}},"getTextExpression":{".class":"SymbolTableNode","kind":"Mdef","node":{".class":"FuncDef","abstract_status":0,"arg_kinds":[0],"arg_names":["self"],"dataclass_transform_spec":null,"deprecated":null,"flags":[],"fullname":"music21.repeat.RepeatExpression.getTextExpression","name":"getTextExpression","type":null}},"isValidText":{".class":"SymbolTableNode","kind":"Mdef","node":{".class":"FuncDef","abstract_status":0,"arg_kinds":[0,0],"arg_names":["self","value"],"dataclass_transform_spec":null,"deprecated":null,"flags":[],"fullname":"music21.repeat.RepeatExpression.isValidText","name":"isValidText","type":null}},"setText":{".class":"SymbolTableNode","kind":"Mdef","node":{".class":"FuncDef","abstract_status":0,"arg_kinds":[0,0],"arg_names":["self","value"],"dataclass_transform_spec":null,"deprecated":null,"flags":[],"fullname":"music21.repeat.RepeatExpression.setText","name":"setText","type":null}},"setTextExpression":{".class":"SymbolTableNode","kind":"Mdef","node":{".class":"FuncDef","abstract_status":0,"arg_kinds":[0,0],"arg_names":["self","value"],"dataclass_transform_spec":null,"deprecated":null,"flags":[],"fullname":"music21.repeat.RepeatExpression.setTextExpression","name":"setTextExpression","type":null}},"useSymbol":{".class":"SymbolTableNode","implicit":true,"kind":"Mdef","node":{".class":"Var","flags":["is_inferred"],"fullname":"music21.repeat.RepeatExpression.useSymbol","name":"useSymbol","type":{".class":"AnyType","missing_import_name":null,"source_any":null,"type_of_any":1}}}},"self_type":{".class":"TypeVarType","default":{".class":"AnyType","missing_import_name":null,"source_any":null,"type_of_any":4},"fullname":"music21.repeat.RepeatExpression.Self","id":0,"name":"Self","namespace":"","upper_bound":"music21.repeat.RepeatExpression","values":[],"variance":0},"slots":null,"tuple_type":null,"type_vars":[],"typeddict_type":null}},"RepeatExpressionCommand":{".class":"SymbolTableNode","kind":"Gdef","node":{".class":"TypeInfo","_promote":[],"abstract_attributes":[],"alt_promote":null,"bases":["music21.repeat.RepeatExpression"],"dataclass_transform_spec":null,"declared_metaclass":null,"defn":{".class":"ClassDef","fullname":"music21.repeat.RepeatExpressionCommand","name":"RepeatExpressionCommand","type_vars":[]},"deletable_attributes":[],"deprecated":null,"flags":[],"fullname":"music21.repeat.RepeatExpressionCommand","has_param_spec_type":false,"metaclass_type":null,"metadata":{},"module_name":"music21.repeat","mro":["music21.repeat.RepeatExpressionCommand","music21.repeat.RepeatExpression","music21.repeat.RepeatMark","music21.expressions.Expression","music21.base.Music21Object","music21.prebase.ProtoM21Object","builtins.object"],"names":{".class":"SymbolTable","__init__":{".class":"SymbolTableNode","kind":"Mdef","node":{".class":"FuncDef","abstract_status":0,"arg_kinds":[0,4],"arg_names":["self","keywords"],"dataclass_transform_spec":null,"deprecated":null,"flags":[],"fullname":"music21.repeat.RepeatExpressionCommand.__init__","name":"__init__","type":null}},"repeatAfterJump":{".class":"SymbolTableNode","implicit":true,"kind":"Mdef","node":{".class":"Var","flags":["is_inferred"],"fullname":"music21.repeat.RepeatExpressionCommand.repeatAfterJump","name":"repeatAfterJump","type":{".class":"AnyType","missing_import_name":null,"source_any":null,"type_of_any":1}}}},"self_type":{".class":"TypeVarType","default":{".class":"AnyType","missing_import_name":null,"source_any":null,"type_of_any":4},"fullname":"music21.repeat.RepeatExpressionCommand.Self","id":0,"name":"Self","namespace":"","upper_bound":"music21.repeat.RepeatExpressionCommand","values":[],"variance":0},"slots":null,"tuple_type":null,"type_vars":[],"typeddict_type":null}},"RepeatExpressionException":{".class":"SymbolTableNode","kind":"Gdef","node":{".class":"TypeInfo","_promote":[],"abstract_attributes":[],"alt_promote":null,"bases":["music21.exceptions21.Music21Exception"],"dataclass_transform_spec":null,"declared_metaclass":null,"defn":{".class":"ClassDef","fullname":"music21.repeat.RepeatExpressionException","name":"RepeatExpressionException","type_vars":[]},"deletable_attributes":[],"deprecated":null,"flags":[],"fullname":"music21.repeat.RepeatExpressionException","has_param_spec_type":false,"metaclass_type":null,"metadata":{},"module_name":"music21.repeat","mro":["music21.repeat.RepeatExpressionException","music21.exceptions21.Music21Exception","builtins.Exception","builtins.BaseException","builtins.object"],"names":{".class":"SymbolTable"},"self_type":{".class":"TypeVarType","default":{".class":"AnyType","missing_import_name":null,"source_any":null,"type_of_any":4},"fullname":"music21.repeat.RepeatExpressionException.Self","id":0,"name":"Self","namespace":"","upper_bound":"music21.repeat.RepeatExpressionException","values":[],"variance":0},"slots":null,"tuple_type":null,"type_vars":[],"typeddict_type":null}},"RepeatExpressionMarker":{".class":"SymbolTableNode","kind":"Gdef","node":{".class":"TypeInfo","_promote":[],"abstract_attributes":[],"alt_promote":null,"bases":["music21.repeat.RepeatExpression"],"dataclass_transform_spec":null,"declared_metaclass":null,"defn":{".class":"ClassDef","fullname":"music21.repeat.RepeatExpressionMarker","name":"RepeatExpressionMarker","type_vars":[]},"deletable_attributes":[],"deprecated":null,"flags":[],"fullname":"music21.repeat.RepeatExpressionMarker","has_param_spec_type":false,"metaclass_type":null,"metadata":{},"module_name":"music21.repeat","mro":["music21.repeat.RepeatExpressionMarker","music21.repeat.RepeatExpression","music21.repeat.RepeatMark","music21.expressions.Expression","music21.base.Music21Object","music21.prebase.ProtoM21Object","builtins.object"],"names":{".class":"SymbolTable","__init__":{".class":"SymbolTableNode","kind":"Mdef","node":{".class":"FuncDef","abstract_status":0,"arg_kinds":[0,4],"arg_names":["self","keywords"],"dataclass_transform_spec":null,"deprecated":null,"flags":[],"fullname":"music21.repeat.RepeatExpressionMarker.__init__","name":"__init__","type":null}}},"self_type":{".class":"TypeVarType","default":{".class":"AnyType","missing_import_name":null,"source_any":null,"type_of_any":4},"fullname":"music21.repeat.RepeatExpressionMarker.Self","id":0,"name":"Self","namespace":"","upper_bound":"music21.repeat.RepeatExpressionMarker","values":[],"variance":0},"slots":null,"tuple_type":null,"type_vars":[],"typeddict_type":null}},"RepeatFinder":{".class":"SymbolTableNode","kind":"Gdef","node":{".class":"TypeInfo","_promote":[],"abstract_attributes":[],"alt_promote":null,"bases":["builtins.object"],"dataclass_transform_spec":null,"declared_metaclass":null,"defn":{".class":"ClassDef","fullname":"music21.repeat.RepeatFinder","name":"RepeatFinder","type_vars":[]},"deletable_attributes":[],"deprecated":null,"flags":[],"fullname":"music21.repeat.RepeatFinder","has_param_spec_type":false,"metaclass_type":null,"metadata":{},"module_name":"music21.repeat","mro":["music21.repeat.RepeatFinder","builtins.object"],"names":{".class":"SymbolTable","_DOC_ATTR":{".class":"SymbolTableNode","kind":"Mdef","node":{".class":"Var","flags":["is_initialized_in_class","is_ready","has_explicit_value"],"fullname":"music21.repeat.RepeatFinder._DOC_ATTR","name":"_DOC_ATTR","type":{".class":"Instance","args":["builtins.str","builtins.str"],"extra_attrs":null,"type_ref":"builtins.dict"}}},"_DOC_ORDER":{".class":"SymbolTableNode","kind":"Mdef","node":{".class":"Var","flags":["is_initialized_in_class","is_inferred","has_explicit_value"],"fullname":"music21.repeat.RepeatFinder._DOC_ORDER","name":"_DOC_ORDER","type":{".class":"Instance","args":["builtins.str"],"extra_attrs":null,"type_ref":"builtins.list"}}},"__init__":{".class":"SymbolTableNode","kind":"Mdef","node":{".class":"FuncDef","abstract_status":0,"arg_kinds":[0,1,1],"arg_names":["self","inpStream","defaultMeasureHashFunction"],"dataclass_transform_spec":null,"deprecated":null,"flags":[],"fullname":"music21.repeat.RepeatFinder.__init__","name":"__init__","type":null}},"_getSimilarMeasureTuples":{".class":"SymbolTableNode","kind":"Mdef","node":{".class":"FuncDef","abstract_status":0,"arg_kinds":[0,0,1],"arg_names":["self","mList","hasPickup"],"dataclass_transform_spec":null,"deprecated":null,"flags":[],"fullname":"music21.repeat.RepeatFinder._getSimilarMeasureTuples","name":"_getSimilarMeasureTuples","type":null}},"_getSimilarMeasuresHelper":{".class":"SymbolTableNode","kind":"Mdef","node":{".class":"FuncDef","abstract_status":0,"arg_kinds":[0,0,0,0,0,0],"arg_names":["self","measures","source","compare","resDict","useDict"],"dataclass_transform_spec":null,"deprecated":null,"flags":[],"fullname":"music21.repeat.RepeatFinder._getSimilarMeasuresHelper","name":"_getSimilarMeasuresHelper","type":null}},"_mGroups":{".class":"SymbolTableNode","implicit":true,"kind":"Mdef","node":{".class":"Var","flags":["is_inferred"],"fullname":"music21.repeat.RepeatFinder._mGroups","name":"_mGroups","type":{".class":"AnyType","missing_import_name":null,"source_any":null,"type_of_any":1}}},"_mList":{".class":"SymbolTableNode","implicit":true,"kind":"Mdef","node":{".class":"Var","flags":["is_inferred"],"fullname":"music21.repeat.RepeatFinder._mList","name":"_mList","type":{".class":"AnyType","missing_import_name":null,"source_any":null,"type_of_any":1}}},"correctMeasureNumbers":{".class":"SymbolTableNode","implicit":true,"kind":"Mdef","node":{".class":"Var","flags":["is_inferred"],"fullname":"music21.repeat.RepeatFinder.correctMeasureNumbers","name":"correctMeasureNumbers","type":{".class":"AnyType","missing_import_name":null,"source_any":null,"type_of_any":1}}},"defaultHash":{".class":"SymbolTableNode","implicit":true,"kind":"Mdef","node":{".class":"Var","flags":["is_inferred"],"fullname":"music21.repeat.RepeatFinder.defaultHash","name":"defaultHash","type":{".class":"AnyType","missing_import_name":null,"source_any":null,"type_of_any":1}}},"getMeasureSimilarityList":{".class":"SymbolTableNode","kind":"Mdef","node":{".class":"FuncDef","abstract_status":0,"arg_kinds":[0],"arg_names":["self"],"dataclass_transform_spec":null,"deprecated":null,"flags":[],"fullname":"music21.repeat.RepeatFinder.getMeasureSimilarityList","name":"getMeasureSimilarityList","type":null}},"getQuarterLengthOfPickupMeasure":{".class":"SymbolTableNode","kind":"Mdef","node":{".class":"FuncDef","abstract_status":0,"arg_kinds":[0],"arg_names":["self"],"dataclass_transform_spec":null,"deprecated":null,"flags":[],"fullname":"music21.repeat.RepeatFinder.getQuarterLengthOfPickupMeasure","name":"getQuarterLengthOfPickupMeasure","type":null}},"getSimilarMeasureGroups":{".class":"SymbolTableNode","kind":"Mdef","node":{".class":"FuncDef","abstract_status":0,"arg_kinds":[0,1],"arg_names":["self","threshold"],"dataclass_transform_spec":null,"deprecated":null,"flags":[],"fullname":"music21.repeat.RepeatFinder.getSimilarMeasureGroups","name":"getSimilarMeasureGroups","type":null}},"hasPickup":{".class":"SymbolTableNode","kind":"Mdef","node":{".class":"FuncDef","abstract_status":0,"arg_kinds":[0],"arg_names":["self"],"dataclass_transform_spec":null,"deprecated":null,"flags":[],"fullname":"music21.repeat.RepeatFinder.hasPickup","name":"hasPickup","type":null}},"s":{".class":"SymbolTableNode","implicit":true,"kind":"Mdef","node":{".class":"Var","flags":["is_inferred"],"fullname":"music21.repeat.RepeatFinder.s","name":"s","type":{".class":"AnyType","missing_import_name":null,"source_any":null,"type_of_any":1}}},"simplify":{".class":"SymbolTableNode","kind":"Mdef","node":{".class":"FuncDef","abstract_status":0,"arg_kinds":[0,1,1,5],"arg_names":["self","repeatThreshold","repeatEndingThreshold","inPlace"],"dataclass_transform_spec":null,"deprecated":null,"flags":[],"fullname":"music21.repeat.RepeatFinder.simplify","name":"simplify","type":null}}},"self_type":{".class":"TypeVarType","default":{".class":"AnyType","missing_import_name":null,"source_any":null,"type_of_any":4},"fullname":"music21.repeat.RepeatFinder.Self","id":0,"name":"Self","namespace":"","upper_bound":"music21.repeat.RepeatFinder","values":[],"variance":0},"slots":null,"tuple_type":null,"type_vars":[],"typeddict_type":null}},"RepeatMark":{".class":"SymbolTableNode","kind":"Gdef","node":{".class":"TypeInfo","_promote":[],"abstract_attributes":[],"alt_promote":null,"bases":["music21.prebase.ProtoM21Object"],"dataclass_transform_spec":null,"declared_metaclass":null,"defn":{".class":"ClassDef","fullname":"music21.repeat.RepeatMark","name":"RepeatMark","type_vars":[]},"deletable_attributes":[],"deprecated":null,"flags":[],"fullname":"music21.repeat.RepeatMark","has_param_spec_type":false,"metaclass_type":null,"metadata":{},"module_name":"music21.repeat","mro":["music21.repeat.RepeatMark","music21.prebase.ProtoM21Object","builtins.object"],"names":{".class":"SymbolTable"},"self_type":{".class":"TypeVarType","default":{".class":"AnyType","missing_import_name":null,"source_any":null,"type_of_any":4},"fullname":"music21.repeat.RepeatMark.Self","id":0,"name":"Self","namespace":"","upper_bound":"music21.repeat.RepeatMark","values":[],"variance":0},"slots":null,"tuple_type":null,"type_vars":[],"typeddict_type":null}},"Segno":{".class":"SymbolTableNode","kind":"Gdef","node":{".class":"TypeInfo","_promote":[],"abstract_attributes":[],"alt_promote":null,"bases":["music21.repeat.RepeatExpressionMarker"],"dataclass_transform_spec":null,"declared_metaclass":null,"defn":{".class":"ClassDef","fullname":"music21.repeat.Segno","name":"Segno","type_vars":[]},"deletable_attributes":[],"deprecated":null,"flags":[],"fullname":"music21.repeat.Segno","has_param_spec_type":false,"metaclass_type":null,"metadata":{},"module_name":"music21.repeat","mro":["music21.repeat.Segno","music21.repeat.RepeatExpressionMarker","music21.repeat.RepeatExpression","music21.repeat.RepeatMark","music21.expressions.Expression","music21.base.Music21Object","music21.prebase.ProtoM21Object","builtins.object"],"names":{".class":"SymbolTable","__init__":{".class":"SymbolTableNode","kind":"Mdef","node":{".class":"FuncDef","abstract_status":0,"arg_kinds":[0,4],"arg_names":["self","keywords"],"dataclass_transform_spec":null,"deprecated":null,"flags":[],"fullname":"music21.repeat.Segno.__init__","name":"__init__","type":null}}},"self_type":{".class":"TypeVarType","default":{".class":"AnyType","missing_import_name":null,"source_any":null,"type_of_any":4},"fullname":"music21.repeat.Segno.Self","id":0,"name":"Self","namespace":"","upper_bound":"music21.repeat.Segno","values":[],"variance":0},"slots":null,"tuple_type":null,"type_vars":[],"typeddict_type":null}},"StreamType":{".class":"SymbolTableNode","cross_ref":"music21.common.types.StreamType","kind":"Gdef"},"UnequalPartsLengthException":{".class":"SymbolTableNode","kind":"Gdef","node":{".class":"TypeInfo","_promote":[],"abstract_attributes":[],"alt_promote":null,"bases":["music21.exceptions21.Music21Exception"],"dataclass_transform_spec":null,"declared_metaclass":null,"defn":{".class":"ClassDef","fullname":"music21.repeat.UnequalPartsLengthException","name":"UnequalPartsLengthException","type_vars":[]},"deletable_attributes":[],"deprecated":null,"flags":[],"fullname":"music21.repeat.UnequalPartsLengthException","has_param_spec_type":false,"metaclass_type":null,"metadata":{},"module_name":"music21.repeat","mro":["music21.repeat.UnequalPartsLengthException","music21.exceptions21.Music21Exception","builtins.Exception","builtins.BaseException","builtins.object"],"names":{".class":"SymbolTable"},"self_type":{".class":"TypeVarType","default":{".class":"AnyType","missing_import_name":null,"source_any":null,"type_of_any":4},"fullname":"music21.repeat.UnequalPartsLengthException.Self","id":0,"name":"Self","namespace":"","upper_bound":"music21.repeat.UnequalPartsLengthException","values":[],"variance":0},"slots":null,"tuple_type":null,"type_vars":[],"typeddict_type":null}},"_DOC_ORDER":{".class":"SymbolTableNode","kind":"Gdef","node":{".class":"Var","flags":["is_inferred","has_explicit_value"],"fullname":"music21.repeat._DOC_ORDER","name":"_DOC_ORDER","type":{".class":"Instance","args":["builtins.type"],"extra_attrs":null,"type_ref":"builtins.list"}}},"__annotations__":{".class":"SymbolTableNode","kind":"Gdef","node":{".class":"Var","flags":["is_ready"],"fullname":"music21.repeat.__annotations__","name":"__annotations__","type":{".class":"Instance","args":["builtins.str",{".class":"AnyType","missing_import_name":null,"source_any":null,"type_of_any":6}],"extra_attrs":null,"type_ref":"builtins.dict"}}},"__doc__":{".class":"SymbolTableNode","kind":"Gdef","node":{".class":"Var","flags":["is_ready"],"fullname":"music21.repeat.__doc__","name":"__doc__","type":"builtins.str"}},"__file__":{".class":"SymbolTableNode","kind":"Gdef","node":{".class":"Var","flags":["is_ready"],"fullname":"music21.repeat.__file__","name":"__file__","type":"builtins.str"}},"__name__":{".class":"SymbolTableNode","kind":"Gdef","node":{".class":"Var","flags":["is_ready"],"fullname":"music21.repeat.__name__","name":"__name__","type":"builtins.str"}},"__package__":{".class":"SymbolTableNode","kind":"Gdef","node":{".class":"Var","flags":["is_ready"],"fullname":"music21.repeat.__package__","name":"__package__","type":"builtins.str"}},"__spec__":{".class":"SymbolTableNode","kind":"Gdef","node":{".class":"Var","flags":["is_ready"],"fullname":"music21.repeat.__spec__","name":"__spec__","type":"_frozen_importlib.ModuleSpec"}},"annotations":{".class":"SymbolTableNode","cross_ref":"__future__.annotations","kind":"Gdef"},"copy":{".class":"SymbolTableNode","cross_ref":"copy","kind":"Gdef"},"deleteMeasures":{".class":"SymbolTableNode","kind":"Gdef","node":{".class":"FuncDef","abstract_status":0,"arg_kinds":[0,0,5,5],"arg_names":["s","toDelete","inPlace","correctMeasureNumbers"],"dataclass_transform_spec":null,"deprecated":null,"flags":[],"fullname":"music21.repeat.deleteMeasures","name":"deleteMeasures","type":null}},"environLocal":{".class":"SymbolTableNode","kind":"Gdef","node":{".class":"Var","flags":["is_inferred","has_explicit_value"],"fullname":"music21.repeat.environLocal","name":"environLocal","type":"music21.environment.Environment"}},"environment":{".class":"SymbolTableNode","cross_ref":"music21.environment","kind":"Gdef"},"exceptions21":{".class":"SymbolTableNode","cross_ref":"music21.exceptions21","kind":"Gdef"},"expressions":{".class":"SymbolTableNode","cross_ref":"music21.expressions","kind":"Gdef"},"insertRepeat":{".class":"SymbolTableNode","kind":"Gdef","node":{".class":"FuncDef","abstract_status":0,"arg_kinds":[0,0,0,5],"arg_names":["s","start","end","inPlace"],"dataclass_transform_spec":null,"deprecated":null,"flags":[],"fullname":"music21.repeat.insertRepeat","name":"insertRepeat","type":null}},"insertRepeatEnding":{".class":"SymbolTableNode","kind":"Gdef","node":{".class":"FuncDef","abstract_status":0,"arg_kinds":[0,0,0,1,5],"arg_names":["s","start","end","endingNumber","inPlace"],"dataclass_transform_spec":null,"deprecated":null,"flags":[],"fullname":"music21.repeat.insertRepeatEnding","name":"insertRepeatEnding","type":{".class":"CallableType","arg_kinds":[0,0,0,1,5],"arg_names":["s","start","end","endingNumber","inPlace"],"arg_types":[{".class":"AnyType","missing_import_name":null,"source_any":null,"type_of_any":1},{".class":"AnyType","missing_import_name":null,"source_any":null,"type_of_any":1},{".class":"AnyType","missing_import_name":null,"source_any":null,"type_of_any":1},"builtins.int",{".class":"AnyType","missing_import_name":null,"source_any":null,"type_of_any":1}],"bound_args":[],"def_extras":{"first_arg":null},"fallback":"builtins.function","from_concatenate":false,"implicit":false,"imprecise_arg_kinds":false,"is_ellipsis_args":false,"name":"insertRepeatEnding","ret_type":{".class":"AnyType","missing_import_name":null,"source_any":null,"type_of_any":1},"type_guard":null,"type_is":null,"unpack_kwargs":false,"variables":[]}}},"music21":{".class":"SymbolTableNode","cross_ref":"music21","kind":"Gdef"},"prebase":{".class":"SymbolTableNode","cross_ref":"music21.prebase","kind":"Gdef"},"repeatExpressionReference":{".class":"SymbolTableNode","kind":"Gdef","node":{".class":"Var","flags":["is_inferred","has_explicit_value"],"fullname":"music21.repeat.repeatExpressionReference","name":"repeatExpressionReference","type":{".class":"Instance","args":["music21.repeat.RepeatExpression"],"extra_attrs":null,"type_ref":"builtins.list"}}},"spanner":{".class":"SymbolTableNode","cross_ref":"music21.spanner","kind":"Gdef"},"stream":{".class":"SymbolTableNode","cross_ref":"music21.stream","kind":"Gdef"},"string":{".class":"SymbolTableNode","cross_ref":"string","kind":"Gdef"},"style":{".class":"SymbolTableNode","cross_ref":"music21.style","kind":"Gdef"},"t":{".class":"SymbolTableNode","cross_ref":"typing","kind":"Gdef"}},"path":"C:\\Users\\12502\\AppData\\Roaming\\Python\\Python313\\site-packages\\music21\\repeat.py"}